flixbusapi/__init__.py
flixbusapi-0.1.dist-info/DESCRIPTION.rst
flixbusapi-0.1.dist-info/METADATA
flixbusapi-0.1.dist-info/RECORD
flixbusapi-0.1.dist-info/WHEEL
flixbusapi-0.1.dist-info/metadata.json
flixbusapi-0.1.dist-info/top_level.txt
