Metadata-Version: 2.0
Name: flixbusapi
Version: 0.1
Summary: FlixBus API client for Python
Home-page: https://github.com/zlatkoc/flixbusapi
Author: Zlatko Cajic
Author-email: UNKNOWN
License: MIT
Platform: UNKNOWN
